kopiccino/__about__.py
kopiccino/__init__.py
kopiccino/__main__.py
kopiccino/abstract.py
kopiccino/bootstrap.py
kopiccino/cli.py
kopiccino/config.py
kopiccino/exceptions.py
kopiccino/utils.py
kopiccino-1.0.0a1.dist-info/LICENSE.txt
kopiccino-1.0.0a1.dist-info/METADATA
kopiccino-1.0.0a1.dist-info/WHEEL
kopiccino-1.0.0a1.dist-info/top_level.txt
kopiccino-1.0.0a1.dist-info/RECORD
