Metadata-Version: 2.1
Name: kopiccino
Version: 1.0.0a1
Summary: Script sharing made simple.
Home-page: https://github.com/onyxware/kopiccino
Author: Ong Yong Xin
Author-email: ongyongxin.offical@gmail.com
License: UNKNOWN
Platform: UNKNOWN
Classifier: Programming Language :: Python :: 3
Classifier: License :: OSI Approved :: MIT License
Classifier: Operating System :: OS Independent
Requires-Python: >=3.7
Requires-Dist: requests (>=2.21.0)
Requires-Dist: toml (>=0.10.0)
Requires-Dist: colorlog (>=4.1.0)
Requires-Dist: userdefaults3 (>=1.1.6)
